{"version":1.2,"people":[{"pose_keypoints_2d":[-1,-1,0,-1,-1,0,-0.27008,-0.895055,0.312637,-0.227142,-0.426397,0.363134,-0.178143,0.0204519,0.507249,-1,-1,0,-1,-1,0,-1,-1,0,-1,-1,0,-1,-1,0,-1,-1,0,-1,-1,0,-1,-1,0,-1,-1,0,-1,-1,0,-1,-1,0,-1,-1,0,-1,-1,0],"face_keypoints_2d":[-1,-1,0,-1,-1,0,-1,-1,0,-1,-1,0,-1,-1,0,-1,-1,0,-1,-1,0,-1,-1,0,-1,-1,0,-1,-1,0,-1,-1,0,-1,-1,0,-1,-1,0,-1,-1,0,-1,-1,0,-1,-1,0,-1,-1,0,-1,-1,0,-1,-1,0,-1,-1,0,-1,-1,0,-1,-1,0,-1,-1,0,-1,-1,0,-1,-1,0,-1,-1,0,-1,-1,0,-1,-1,0,-1,-1,0,-1,-1,0,-1,-1,0,-1,-1,0,-1,-1,0,-1,-1,0,-1,-1,0,-1,-1,0,-1,-1,0,-1,-1,0,-1,-1,0,-1,-1,0,-1,-1,0,-1,-1,0,-1,-1,0,-1,-1,0,-1,-1,0,-1,-1,0,-1,-1,0,-1,-1,0,-1,-1,0,-1,-1,0,-1,-1,0,-1,-1,0,-1,-1,0,-1,-1,0,-1,-1,0,-1,-1,0,-1,-1,0,-1,-1,0,-1,-1,0,-1,-1,0,-1,-1,0,-1,-1,0,-1,-1,0,-1,-1,0,-1,-1,0,-1,-1,0,-1,-1,0,-1,-1,0,-1,-1,0,-1,-1,0],"hand_left_keypoints_2d":[],"hand_right_keypoints_2d":[],"pose_keypoints_3d":[],"face_keypoints_3d":[],"hand_left_keypoints_3d":[],"hand_right_keypoints_3d":[]},{"pose_keypoints_2d":[-1,-1,0,-1,-1,0,-1,-1,0,-1,-1,0,-1,-1,0,-0.521445,-0.933335,0.0714835,-0.527527,-0.475508,0.384004,-0.499962,-0.0939773,0.731551,-1,-1,0,-1,-1,0,-1,-1,0,-1,-1,0,-1,-1,0,-1,-1,0,-1,-1,0,-1,-1,0,-1,-1,0,-1,-1,0],"face_keypoints_2d":[-1,-1,0,-1,-1,0,-1,-1,0,-1,-1,0,-1,-1,0,-1,-1,0,-1,-1,0,-1,-1,0,-1,-1,0,-1,-1,0,-1,-1,0,-1,-1,0,-1,-1,0,-1,-1,0,-1,-1,0,-1,-1,0,-1,-1,0,-1,-1,0,-1,-1,0,-1,-1,0,-1,-1,0,-1,-1,0,-1,-1,0,-1,-1,0,-1,-1,0,-1,-1,0,-1,-1,0,-1,-1,0,-1,-1,0,-1,-1,0,-1,-1,0,-1,-1,0,-1,-1,0,-1,-1,0,-1,-1,0,-1,-1,0,-1,-1,0,-1,-1,0,-1,-1,0,-1,-1,0,-1,-1,0,-1,-1,0,-1,-1,0,-1,-1,0,-1,-1,0,-1,-1,0,-1,-1,0,-1,-1,0,-1,-1,0,-1,-1,0,-1,-1,0,-1,-1,0,-1,-1,0,-1,-1,0,-1,-1,0,-1,-1,0,-1,-1,0,-1,-1,0,-1,-1,0,-1,-1,0,-1,-1,0,-1,-1,0,-1,-1,0,-1,-1,0,-1,-1,0,-1,-1,0,-1,-1,0,-1,-1,0,-1,-1,0,-1,-1,0],"hand_left_keypoints_2d":[],"hand_right_keypoints_2d":[],"pose_keypoints_3d":[],"face_keypoints_3d":[],"hand_left_keypoints_3d":[],"hand_right_keypoints_3d":[]},{"pose_keypoints_2d":[-1,-1,0,-0.39572,-0.933197,0.382894,-1,-1,0,-1,-1,0,-1,-1,0,-1,-1,0,-1,-1,0,-1,-1,0,-0.300752,-0.0994285,0.381833,-0.251704,0.336612,0.332032,-0.242525,0.728943,0.0823477,-0.426352,-0.110266,0.391994,-0.374158,0.35287,0.414907,-0.358998,0.734373,0.0799877,-1,-1,0,-1,-1,0,-1,-1,0,-1,-1,0],"face_keypoints_2d":[-1,-1,0,-1,-1,0,-1,-1,0,-1,-1,0,-1,-1,0,-1,-1,0,-1,-1,0,-1,-1,0,-1,-1,0,-1,-1,0,-1,-1,0,-1,-1,0,-1,-1,0,-1,-1,0,-1,-1,0,-1,-1,0,-1,-1,0,-1,-1,0,-1,-1,0,-1,-1,0,-1,-1,0,-1,-1,0,-1,-1,0,-1,-1,0,-1,-1,0,-1,-1,0,-1,-1,0,-1,-1,0,-1,-1,0,-1,-1,0,-1,-1,0,-1,-1,0,-1,-1,0,-1,-1,0,-1,-1,0,-1,-1,0,-1,-1,0,-1,-1,0,-1,-1,0,-1,-1,0,-1,-1,0,-1,-1,0,-1,-1,0,-1,-1,0,-1,-1,0,-1,-1,0,-1,-1,0,-1,-1,0,-1,-1,0,-1,-1,0,-1,-1,0,-1,-1,0,-1,-1,0,-1,-1,0,-1,-1,0,-1,-1,0,-1,-1,0,-1,-1,0,-1,-1,0,-1,-1,0,-1,-1,0,-1,-1,0,-1,-1,0,-1,-1,0,-1,-1,0,-1,-1,0,-1,-1,0,-1,-1,0,-1,-1,0,-1,-1,0],"hand_left_keypoints_2d":[],"hand_right_keypoints_2d":[],"pose_keypoints_3d":[],"face_keypoints_3d":[],"hand_left_keypoints_3d":[],"hand_right_keypoints_3d":[]}]}