{"version":1.2,"people":[{"pose_keypoints_2d":[0.238371,-0.0939844,0.0665801,-1,-1,0,-1,-1,0,-1,-1,0,-1,-1,0,-1,-1,0,-1,-1,0,-1,-1,0,-1,-1,0,-1,-1,0,-1,-1,0,-1,-1,0,-1,-1,0,-1,-1,0,-1,-1,0,0.244632,-0.153744,0.656338,-1,-1,0,0.364051,-0.290127,0.0691701],"face_keypoints_2d":[-1,-1,0,-1,-1,0,-1,-1,0,-1,-1,0,-1,-1,0,-1,-1,0,-1,-1,0,-1,-1,0,-1,-1,0,-1,-1,0,-1,-1,0,-1,-1,0,-1,-1,0,-1,-1,0,-1,-1,0,-1,-1,0,-1,-1,0,-1,-1,0,-1,-1,0,-1,-1,0,-1,-1,0,-1,-1,0,-1,-1,0,-1,-1,0,-1,-1,0,-1,-1,0,-1,-1,0,-1,-1,0,-1,-1,0,-1,-1,0,-1,-1,0,-1,-1,0,-1,-1,0,-1,-1,0,-1,-1,0,-1,-1,0,-1,-1,0,-1,-1,0,-1,-1,0,-1,-1,0,-1,-1,0,-1,-1,0,-1,-1,0,-1,-1,0,-1,-1,0,-1,-1,0,-1,-1,0,-1,-1,0,-1,-1,0,-1,-1,0,-1,-1,0,-1,-1,0,-1,-1,0,-1,-1,0,-1,-1,0,-1,-1,0,-1,-1,0,-1,-1,0,-1,-1,0,-1,-1,0,-1,-1,0,-1,-1,0,-1,-1,0,-1,-1,0,-1,-1,0,-1,-1,0,-1,-1,0,-1,-1,0,-1,-1,0,-1,-1,0],"hand_left_keypoints_2d":[],"hand_right_keypoints_2d":[],"pose_keypoints_3d":[],"face_keypoints_3d":[],"hand_left_keypoints_3d":[],"hand_right_keypoints_3d":[]},{"pose_keypoints_2d":[0.0913851,0.145724,0.24646,-1,-1,0,-1,-1,0,-1,-1,0,-1,-1,0,-1,-1,0,-1,-1,0,-1,-1,0,-1,-1,0,-1,-1,0,-1,-1,0,-1,-1,0,-1,-1,0,-1,-1,0,-0.0832399,-0.0993677,0.436454,0.0637716,-0.0232132,0.098547,-0.279284,-0.0503299,0.158029,-1,-1,0],"face_keypoints_2d":[-1,-1,0,-1,-1,0,-1,-1,0,-1,-1,0,-1,-1,0,-1,-1,0,-1,-1,0,-1,-1,0,-1,-1,0,-1,-1,0,-1,-1,0,-1,-1,0,-1,-1,0,-1,-1,0,-1,-1,0,-1,-1,0,-1,-1,0,-1,-1,0,-1,-1,0,-1,-1,0,-1,-1,0,-1,-1,0,-1,-1,0,-1,-1,0,-1,-1,0,-1,-1,0,-1,-1,0,-1,-1,0,-1,-1,0,-1,-1,0,-1,-1,0,-1,-1,0,-1,-1,0,-1,-1,0,-1,-1,0,-1,-1,0,-1,-1,0,-1,-1,0,-1,-1,0,-1,-1,0,-1,-1,0,-1,-1,0,-1,-1,0,-1,-1,0,-1,-1,0,-1,-1,0,-1,-1,0,-1,-1,0,-1,-1,0,-1,-1,0,-1,-1,0,-1,-1,0,-1,-1,0,-1,-1,0,-1,-1,0,-1,-1,0,-1,-1,0,-1,-1,0,-1,-1,0,-1,-1,0,-1,-1,0,-1,-1,0,-1,-1,0,-1,-1,0,-1,-1,0,-1,-1,0,-1,-1,0,-1,-1,0,-1,-1,0,-1,-1,0],"hand_left_keypoints_2d":[],"hand_right_keypoints_2d":[],"pose_keypoints_3d":[],"face_keypoints_3d":[],"hand_left_keypoints_3d":[],"hand_right_keypoints_3d":[]}]}